jobman/__init__.py
jobman/base_logger.py
jobman/cli.py
jobman/core/kill.py
jobman/core/logs.py
jobman/core/ls.py
jobman/core/purge.py
jobman/core/reset.py
jobman/core/run.py
jobman/core/status.py
jobman/exceptions.py
jobman/jobman.py
jobman/nohup.py
jobman/py.typed
jobman/rotating_stdio.py
jobman-0.4.0.dist-info/LICENSE
jobman-0.4.0.dist-info/METADATA
jobman-0.4.0.dist-info/WHEEL
jobman-0.4.0.dist-info/entry_points.txt
jobman-0.4.0.dist-info/RECORD
